[
    {
      "id": 1,
      "title": "Epic Adventures of the Brave Knights: Quest for the Enchanted Kingdom and the Dragons of Destiny",
      "cover": "https://i.ibb.co/bXWhpxP/25080560-7048312.jpg",
      "author": {
        "name": "Sir Arthur Pendragon",
        "image": "https://i.ibb.co/yRXWCcJ/29808799-7605614.jpg"
      },
      "reading_time": 5,
      "publish_date": "2023-08-30",
      "hashtag": "#adventure #knights #dragons #fantasy"
    },
    {
      "id": 2,
      "title": "The Secrets of Time Travel: Unraveling the Mysteries of Temporal Science",
      "cover": "https://i.ibb.co/kDbq5vS/big-word-travel-elements.jpg",
      "author": {
        "name": "Dr. Elizabeth Wells",
        "image": "https://i.ibb.co/P1JQn2F/24488375-6960655.jpg"
      },
      "reading_time": 4,
      "publish_date": "2023-08-28",
      "hashtag": "#timetravel #science #mystery"
    },
    {
      "id": 3,
      "title": "Ancient Civilizations Rediscovered: Archaeological Treasures and Lost Histories",
      "cover": "https://i.ibb.co/SmhspQr/13185423-5121255.jpg",
      "author": {
        "name": "Professor Samuel Carter",
        "image": "https://i.ibb.co/6tvcZ2Q/21532489-6443064.jpg"
      },
      "reading_time": 3,
      "publish_date": "2023-08-25",
      "hashtag": "#archaeology #history #ancientcivilizations"
    },
    {
      "id": 4,
      "title": "Mystical Journeys into the Heart of the Amazon Rainforest: Legends, Lore, and Wildlife",
      "cover": "https://i.ibb.co/gJKQcgX/5169146-2722339.jpg",
      "author": {
        "name": "Adventurer Jane Roberts",
        "image": "https://i.ibb.co/XsDVtKp/13741290-2011-i126-001-old-library-book-interior-set-02.jpg"
      },
      "reading_time": 4,
      "publish_date": "2023-08-23",
      "hashtag": "#amazon #rainforest #adventure"
    },
    {
      "id": 5,
      "title": "The Quantum Enigma: Exploring the Frontiers of Quantum Physics and Parallel Realities",
      "cover": "https://i.ibb.co/c1GcHdP/notebook-surrounded-by-travel-elements.jpg",
      "author": {
        "name": "Dr. Robert Anderson",
        "image": "https://i.ibb.co/xs5SJPk/5202424-Blogpost.jpg"
      },
      "reading_time": 6,
      "publish_date": "2023-08-20",
      "hashtag": "#quantumphysics #science #reality"
    }
  ]
  